CHANGES.rst
CONTRIBUTORS.rst
DEVELOP.rst
LICENSE.GPL
LICENSE.rst
MANIFEST.in
README.rst
setup.cfg
setup.py
docs/index.rst
src/collective/__init__.py
src/collective.consent.egg-info/PKG-INFO
src/collective.consent.egg-info/SOURCES.txt
src/collective.consent.egg-info/dependency_links.txt
src/collective.consent.egg-info/entry_points.txt
src/collective.consent.egg-info/namespace_packages.txt
src/collective.consent.egg-info/not-zip-safe
src/collective.consent.egg-info/requires.txt
src/collective.consent.egg-info/top_level.txt
src/collective/consent/__init__.py
src/collective/consent/configure.zcml
src/collective/consent/interfaces.py
src/collective/consent/permissions.zcml
src/collective/consent/setuphandlers.py
src/collective/consent/subscribers.py
src/collective/consent/subscribers.zcml
src/collective/consent/testing.py
src/collective/consent/upgrades.py
src/collective/consent/upgrades.zcml
src/collective/consent/browser/__init__.py
src/collective/consent/browser/configure.zcml
src/collective/consent/browser/overrides/.gitkeep
src/collective/consent/browser/static/.gitkeep
src/collective/consent/browser/static/main.css
src/collective/consent/browser/static/main.css.map
src/collective/consent/browser/static/main.less
src/collective/consent/browser/static/main.min.css
src/collective/consent/browser/static/main.min.css.map
src/collective/consent/content/__init__.py
src/collective/consent/content/consent_item.py
src/collective/consent/content/consents_container.py
src/collective/consent/locales/README.rst
src/collective/consent/locales/__init__.py
src/collective/consent/locales/collective.consent.pot
src/collective/consent/locales/plone-manual.pot
src/collective/consent/locales/plone.pot
src/collective/consent/locales/update.py
src/collective/consent/locales/update.sh
src/collective/consent/locales/de/LC_MESSAGES/collective.consent.po
src/collective/consent/locales/en/LC_MESSAGES/collective.consent.po
src/collective/consent/profiles/default/browserlayer.xml
src/collective/consent/profiles/default/catalog.xml
src/collective/consent/profiles/default/diff_tool.xml
src/collective/consent/profiles/default/metadata.xml
src/collective/consent/profiles/default/registry.xml
src/collective/consent/profiles/default/repositorytool.xml
src/collective/consent/profiles/default/rolemap.xml
src/collective/consent/profiles/default/types.xml
