Metadata-Version: 2.1
Name: collective.consent
Version: 2.0b1
Summary: Provides a functionality to ask users for consent to different topics.
Home-page: https://pypi.python.org/pypi/collective.consent
Author: Maik Derstappen
Author-email: md@derico.de
License: GPL version 2
Keywords: Python Plone
Platform: UNKNOWN
Classifier: Environment :: Web Environment
Classifier: Framework :: Plone
Classifier: Framework :: Plone :: 5.2
Classifier: Framework :: Plone :: 6.0
Classifier: Framework :: Plone :: Addon
Classifier: Programming Language :: Python
Classifier: Programming Language :: Python :: 3.8
Classifier: Programming Language :: Python :: 3.9
Classifier: Programming Language :: Python :: 3.10
Classifier: Operating System :: OS Independent
Classifier: License :: OSI Approved :: GNU General Public License v2 (GPLv2)
Provides-Extra: test
License-File: LICENSE.GPL
License-File: LICENSE.rst
